renkodf/__init__.py
renkodf/renkodf.py
renkodf-1.1.dist-info/LICENSE.txt
renkodf-1.1.dist-info/METADATA
renkodf-1.1.dist-info/WHEEL
renkodf-1.1.dist-info/top_level.txt
renkodf-1.1.dist-info/RECORD
